linkup_company_research/__init__.py
linkup_company_research/prompts.py
linkup_company_research/schemas.py
linkup_company_research/server.py
linkup_company_research/types.py
linkup_company_research_mcp-0.2.0.dist-info/METADATA
linkup_company_research_mcp-0.2.0.dist-info/WHEEL
linkup_company_research_mcp-0.2.0.dist-info/entry_points.txt
linkup_company_research_mcp-0.2.0.dist-info/RECORD
