Metadata-Version: 2.4
Name: linkup-company-research-mcp
Version: 0.2.0
Summary: Company research MCP server powered by Linkup - 10 research tools with dual output formats (natural language or structured JSON), full parameter control, and optimized prompts for comprehensive company intelligence.
Author-email: Linkup <support@linkup.so>
License: MIT
Keywords: ai,company-research,linkup,llm,mcp
Classifier: Development Status :: 4 - Beta
Classifier: Intended Audience :: Developers
Classifier: License :: OSI Approved :: MIT License
Classifier: Programming Language :: Python :: 3
Classifier: Programming Language :: Python :: 3.10
Classifier: Programming Language :: Python :: 3.11
Classifier: Programming Language :: Python :: 3.12
Requires-Python: >=3.10
Requires-Dist: httpx>=0.27.0
Requires-Dist: mcp>=1.0.0
